nhc2_coco3/__init__.py
nhc2_coco3/coco.py
nhc2_coco3/coco_ca.pem
nhc2_coco3/coco_climate.py
nhc2_coco3/coco_device_class.py
nhc2_coco3/coco_discover.py
nhc2_coco3/coco_discover_profiles.py
nhc2_coco3/coco_entity.py
nhc2_coco3/coco_fan.py
nhc2_coco3/coco_fan_speed.py
nhc2_coco3/coco_generic.py
nhc2_coco3/coco_light.py
nhc2_coco3/coco_login_validation.py
nhc2_coco3/coco_profiles.py
nhc2_coco3/coco_shutter.py
nhc2_coco3/coco_switch.py
nhc2_coco3/coco_switched_fan.py
nhc2_coco3/const.py
nhc2_coco3/helpers.py
nhc2_coco3/tests/credentials_example.py
nhc2_coco3/tests/discover_profiles.py
nhc2_coco3/tests/discover_profiles_by_host.py
nhc2_coco3/tests/test_example.py
nhc2_coco3-1.4.0.2.dist-info/LICENSE
nhc2_coco3-1.4.0.2.dist-info/WHEEL
nhc2_coco3-1.4.0.2.dist-info/METADATA
nhc2_coco3-1.4.0.2.dist-info/RECORD
