Metadata-Version: 2.1
Name: nhc2-coco3
Version: 1.4.0.2
Summary: Python controller for a Niko Home Control II installation
Home-page: https://github.com/filipvh/nhc2-coco
License: MIT
Keywords: niko,coco,nhc,nhc2,home,control,II
Author: filipvh
Classifier: License :: OSI Approved :: MIT License
Classifier: Programming Language :: Python :: 2
Classifier: Programming Language :: Python :: 2.7
Classifier: Programming Language :: Python :: 3
Classifier: Programming Language :: Python :: 3.4
Classifier: Programming Language :: Python :: 3.5
Classifier: Programming Language :: Python :: 3.6
Classifier: Programming Language :: Python :: 3.7
Classifier: Programming Language :: Python :: 3.8
Classifier: Programming Language :: Python :: 3.9
Classifier: Programming Language :: Python :: 3.10
Classifier: Programming Language :: Python :: 3.11
Requires-Dist: get-mac (==0.8.2)
Requires-Dist: netifaces (==0.10.9)
Requires-Dist: paho-mqtt (==1.4.0)
Project-URL: Repository, https://github.com/filipvh/nhc2-coco
